librato_bg/__init__.py
librato_bg/client.py
librato_bg/consumer.py
librato_bg-1.0.6.dist-info/DESCRIPTION.rst
librato_bg-1.0.6.dist-info/METADATA
librato_bg-1.0.6.dist-info/RECORD
librato_bg-1.0.6.dist-info/WHEEL
librato_bg-1.0.6.dist-info/metadata.json
librato_bg-1.0.6.dist-info/top_level.txt
