Metadata-Version: 2.0
Name: librato-bg
Version: 1.0.6
Summary: Enables submitting of Librato events in a background thread
Home-page: https://github.com/nyaruka/python-librato-bg
Author: Nyaruka
Author-email: code@nyaruka.com
License: MIT License
Platform: UNKNOWN
Classifier: Development Status :: 5 - Production/Stable
Classifier: Intended Audience :: Developers
Classifier: Topic :: Software Development :: Libraries
Classifier: License :: OSI Approved :: MIT License
Classifier: Programming Language :: Python :: 2
Classifier: Programming Language :: Python :: 3
Requires-Dist: librato-metrics (==0.8.5)
Requires-Dist: six
